{
  "timestamp": "2025-08-14T04:14:01.136Z",
  "sessionUptime": 137668,
  "totalProcesses": 0,
  "totalOptimizations": 1,
  "errorsHandled": 0,
  "finalProcessCount": 0,
  "phoenixActivations": 0,
  "evolutionLevel": 1,
  "totalDrawdowns": 0,
  "maxDrawdownSurvived": 0,
  "configuration": {
    "maxSymbols": 1000,
    "concurrency": 50,
    "cacheSize": 5000,
    "leonardoPort": "3003",
    "frontendPort": "8080",
    "enableFrontend": true,
    "enableAutoUpdater": true,
    "enableMonitoring": true,
    "enableOptimizations": true,
    "enableQuantumMode": true,
    "enableRealTimeAnalytics": true,
    "enableAdvancedAlgorithms": true,
    "enableMaxLeverage": true,
    "enableAntiLiquidation": true,
    "criticalDrawdownThreshold": 0.03,
    "emergencyDrawdownThreshold": 0.045,
    "phoenixActivationThreshold": 0.07,
    "maxLeverage": 125,
    "adaptiveLeverageEnabled": true,
    "quantumEvolutionEnabled": true,
    "realTimeRiskMonitoring": true
  },
  "antiLiquidationReport": null
}